DataGuru/__init__.py
DataGuru-0.0.2.dist-info/LICENCE.txt
DataGuru-0.0.2.dist-info/METADATA
DataGuru-0.0.2.dist-info/WHEEL
DataGuru-0.0.2.dist-info/top_level.txt
DataGuru-0.0.2.dist-info/RECORD
