Metadata-Version: 2.1
Name: DataGuru
Version: 0.0.2
Summary: The "DataGuru" library is a comprehensive Python toolkit designed to simplify common data analysis tasks for data science students and practitioners. With a focus on ease of use and efficiency, this library provides a range of functions to streamline your data analysis workflow.
Home-page: 
Author: Guna M
Author-email: guna0professional@gmail.com
License: MIT
Keywords: data analysis
Classifier: Development Status :: 5 - Production/Stable
Classifier: Intended Audience :: Education
Classifier: Operating System :: OS Independent
Classifier: License :: OSI Approved :: MIT License
Classifier: Programming Language :: Python :: 3
Requires-Python: >=3.6
License-File: LICENCE.txt
Requires-Dist: plotly
Requires-Dist: pandas
Requires-Dist: numpy
Requires-Dist: scipy
